README.md
setup.py
nlp_postprocessor/__init__.py
nlp_postprocessor/postprocessing_functions.py
nlp_postprocessor/postprocessing_pattern.py
nlp_postprocessor/postprocessing_rule.py
nlp_postprocessor/postprocessor.py
nlp_postprocessor/postprocessor_rules.py
nlp_postprocessor.egg-info/PKG-INFO
nlp_postprocessor.egg-info/SOURCES.txt
nlp_postprocessor.egg-info/dependency_links.txt
nlp_postprocessor.egg-info/requires.txt
nlp_postprocessor.egg-info/top_level.txt