Metadata-Version: 2.1
Name: nlp-postprocessor
Version: 0.0.1
Summary: A spaCy component for executing custom logic at the end of a pipeline.
Home-page: UNKNOWN
Author: medSpaCy
Author-email: medspacy.dev@gmail.com
License: UNKNOWN
Platform: UNKNOWN
